pywalletscan2/__init__.py
pywalletscan2/api.py
pywalletscan2-0.0.8.dist-info/LICENSE
pywalletscan2-0.0.8.dist-info/METADATA
pywalletscan2-0.0.8.dist-info/WHEEL
pywalletscan2-0.0.8.dist-info/top_level.txt
pywalletscan2-0.0.8.dist-info/RECORD
