Metadata-Version: 2.1
Name: pywalletscan2
Version: 0.0.8
Summary: A Python Wrapper Implementation of Etherscan
Home-page: https://github.com/efssisbdyy/pywalletscan2
License: MIT
Keywords: ETH,Etherium,Bitcoin,wallet,Etherscan
Classifier: Development Status :: 2 - Pre-Alpha
Classifier: License :: OSI Approved :: MIT License
Classifier: Programming Language :: Python :: 3
License-File: LICENSE
Requires-Dist: aiohttp ==3.9.3
Requires-Dist: aiosignal ==1.3.1
Requires-Dist: async-timeout ==4.0.3
Requires-Dist: attrs ==23.2.0
Requires-Dist: bitarray ==2.9.2
Requires-Dist: certifi ==2024.2.2
Requires-Dist: charset-normalizer ==3.3.2
Requires-Dist: cytoolz ==0.12.3
Requires-Dist: eth-abi ==5.0.0
Requires-Dist: eth-account ==0.11.0
Requires-Dist: eth-hash ==0.7.0
Requires-Dist: eth-keyfile ==0.8.0
Requires-Dist: eth-keys ==0.5.0
Requires-Dist: eth-rlp ==1.0.1
Requires-Dist: eth-typing ==4.0.0
Requires-Dist: eth-utils ==4.0.0
Requires-Dist: frozenlist ==1.4.1
Requires-Dist: hexbytes ==0.3.1
Requires-Dist: idna ==3.6
Requires-Dist: importlib-resources ==6.1.2
Requires-Dist: jsonschema ==4.21.1
Requires-Dist: jsonschema-specifications ==2023.12.1
Requires-Dist: lru-dict ==1.2.0
Requires-Dist: multidict ==6.0.5
Requires-Dist: parsimonious ==0.9.0
Requires-Dist: pkgutil-resolve-name ==1.3.10
Requires-Dist: protobuf ==4.25.3
Requires-Dist: pycryptodome ==3.20.0
Requires-Dist: pyunormalize ==15.1.0
Requires-Dist: pywalletscan ==0.0.1
Requires-Dist: referencing ==0.33.0
Requires-Dist: regex ==2023.12.25
Requires-Dist: requests ==2.31.0
Requires-Dist: rlp ==4.0.0
Requires-Dist: rpds-py ==0.18.0
Requires-Dist: toolz ==0.12.1
Requires-Dist: typing-extensions ==4.10.0
Requires-Dist: urllib3 ==2.2.1
Requires-Dist: web3 ==6.15.1
Requires-Dist: websockets ==12.0
Requires-Dist: yarl ==1.9.4
Requires-Dist: zipp ==3.17.0
